celery_docker_tools
