Metadata-Version: 1.0
Name: celery-docker-tools
Version: 0.0.5
Summary: Celery Docker tools
Home-page: UNKNOWN
Author: Ellis Percival
Author-email: celery-docker-tools_pypi@failcode.co.uk
License: MIT
Platform: UNKNOWN
